atree.py
atree-1.0.0a1.dist-info/METADATA
atree-1.0.0a1.dist-info/WHEEL
atree-1.0.0a1.dist-info/entry_points.txt
atree-1.0.0a1.dist-info/top_level.txt
atree-1.0.0a1.dist-info/RECORD
