Metadata-Version: 2.1
Name: atree
Version: 1.0.0a1
Summary: An augmented version of the `tree` command
Home-page: https://github.com/aafulei/atree
Author: Aaron Fu Lei
Author-email: aaron.fu@alumni.ust.hk
License: MIT
Platform: UNKNOWN
Classifier: Programming Language :: Python :: 3
Classifier: License :: OSI Approved :: MIT License
Classifier: Operating System :: OS Independent
Classifier: Topic :: System :: Filesystems
Classifier: Topic :: Terminals
Requires-Python: >=3.6
